setup.py
Py0870/APIClient.py
Py0870/__init__.py
Py0870.egg-info/PKG-INFO
Py0870.egg-info/SOURCES.txt
Py0870.egg-info/dependency_links.txt
Py0870.egg-info/not-zip-safe
Py0870.egg-info/requires.txt
Py0870.egg-info/top_level.txt