Metadata-Version: 1.0
Name: Py0870
Version: 1.1
Summary: to update
Home-page: UNKNOWN
Author: Robert Putt
Author-email: rob@puttfamily.co.uk
License: UNKNOWN
Platform: UNKNOWN
